{
  "employees": [
    {
      "firstName": "David",
      "lastName": "Bird",
      "email": "bird11@mctc.edu",
      "password": "123",
      "id": 1
    }
  ],
  "locations": [
    {
      "id": 1,
      "name": "Nashville North",
      "address": "500 Circle Way"
    },
    {
      "id": 2,
      "name": "Nashville South",
      "address": "10101 Binary Court"
    }
  ],
  "animals": [
    {
      "id": 3,
      "name": "rge",
      "breed": "Doberman",
      "speciesId": 2,
      "employeeId": 1
    },
    {
      "id": 4,
      "name": "Moltres",
      "breed": "Parakeet",
      "speciesId": 3,
      "employeeId": 1
    },
    {
      "name": "Articuno",
      "breed": "Penguin",
      "speciesId": 3,
      "employeeId": 1,
      "id": 5
    }
  ],
  "species": [
    {
      "id": 1,
      "name": "Dog"
    },
    {
      "id": 2,
      "name": "Cat"
    },
    {
      "id": 3,
      "name": "Bird"
    }
  ],
  "owners": [
    {
      "id": 1,
      "firstName": "This",
      "lastName": "guy",
      "address": "10101 Binary Court"
    }
  ]
}